{
  "fitnessActivity": "walking",
  "startTime": "2024-09-24T03:41:08.018Z",
  "endTime": "2024-09-24T03:46:49.752Z",
  "duration": "341.734s",
  "segment": [{
    "fitnessActivity": "walking",
    "startTime": "2024-09-24T03:41:08.018Z",
    "endTime": "2024-09-24T03:41:15.068Z"
  }, {
    "fitnessActivity": "walking",
    "startTime": "2024-09-24T03:41:15.068Z",
    "endTime": "2024-09-24T03:46:49.752Z"
  }],
  "aggregate": [{
    "metricName": "com.google.heart_minutes.summary",
    "floatValue": 6.0
  }, {
    "metricName": "com.google.calories.expended",
    "floatValue": 19.1181116293506
  }, {
    "metricName": "com.google.step_count.delta",
    "intValue": 634
  }, {
    "metricName": "com.google.distance.delta",
    "floatValue": 465.4037514000403
  }, {
    "metricName": "com.google.speed.summary",
    "floatValue": 1.4811281829597784
  }, {
    "metricName": "com.google.active_minutes",
    "intValue": 5
  }]
}