{
  "fitnessActivity": "walking",
  "startTime": "2024-12-06T07:46:46.308Z",
  "endTime": "2024-12-06T08:06:08.037Z",
  "duration": "1161.729s",
  "segment": [{
    "fitnessActivity": "walking",
    "startTime": "2024-12-06T07:46:46.308Z",
    "endTime": "2024-12-06T08:06:08.037Z"
  }],
  "aggregate": [{
    "metricName": "com.google.heart_minutes.summary",
    "floatValue": 3.0
  }, {
    "metricName": "com.google.calories.expended",
    "floatValue": 64.9922835
  }, {
    "metricName": "com.google.step_count.delta",
    "intValue": 71
  }, {
    "metricName": "com.google.distance.delta",
    "floatValue": 688.6255706739599
  }, {
    "metricName": "com.google.speed.summary",
    "floatValue": 0.7566166430930599
  }, {
    "metricName": "com.google.active_minutes",
    "intValue": 16
  }]
}