{
  "fitnessActivity": "walking",
  "startTime": "2024-04-09T14:53:05.071Z",
  "endTime": "2024-04-09T14:58:37.538Z",
  "duration": "332.467s",
  "segment": [{
    "fitnessActivity": "walking",
    "startTime": "2024-04-09T14:53:05.071Z",
    "endTime": "2024-04-09T14:53:30.203Z"
  }, {
    "fitnessActivity": "walking",
    "startTime": "2024-04-09T14:53:30.203Z",
    "endTime": "2024-04-09T14:58:37.538Z"
  }],
  "aggregate": [{
    "metricName": "com.google.heart_minutes.summary",
    "floatValue": 8.0
  }, {
    "metricName": "com.google.calories.expended",
    "floatValue": 18.611254694419813
  }, {
    "metricName": "com.google.step_count.delta",
    "intValue": 689
  }, {
    "metricName": "com.google.distance.delta",
    "floatValue": 505.90028041338053
  }, {
    "metricName": "com.google.speed.summary",
    "floatValue": 1.4428825465412927
  }, {
    "metricName": "com.google.active_minutes",
    "intValue": 5
  }]
}