{
  "fitnessActivity": "walking",
  "startTime": "2024-01-18T05:26:35.925Z",
  "endTime": "2024-01-18T05:35:32.293Z",
  "duration": "536.368s",
  "segment": [{
    "fitnessActivity": "walking",
    "startTime": "2024-01-18T05:26:35.925Z",
    "endTime": "2024-01-18T05:26:45.740Z"
  }, {
    "fitnessActivity": "walking",
    "startTime": "2024-01-18T05:26:45.740Z",
    "endTime": "2024-01-18T05:35:32.293Z"
  }],
  "aggregate": [{
    "metricName": "com.google.heart_minutes.summary",
    "floatValue": 7.0
  }, {
    "metricName": "com.google.calories.expended",
    "floatValue": 30.006798278225492
  }, {
    "metricName": "com.google.step_count.delta",
    "intValue": 70
  }, {
    "metricName": "com.google.distance.delta",
    "floatValue": 599.7367677290451
  }, {
    "metricName": "com.google.speed.summary",
    "floatValue": 1.1959525370967572
  }, {
    "metricName": "com.google.active_minutes",
    "intValue": 9
  }]
}