{
  "fitnessActivity": "walking",
  "startTime": "2025-02-01T05:23:47.866Z",
  "endTime": "2025-02-01T05:45:41.840Z",
  "duration": "750.330s",
  "segment": [{
    "fitnessActivity": "walking",
    "startTime": "2025-02-01T05:23:47.866Z",
    "endTime": "2025-02-01T05:24:48.007Z"
  }, {
    "fitnessActivity": "walking",
    "startTime": "2025-02-01T05:30:52.429Z",
    "endTime": "2025-02-01T05:33:12.080Z"
  }, {
    "fitnessActivity": "walking",
    "startTime": "2025-02-01T05:36:31.302Z",
    "endTime": "2025-02-01T05:45:41.840Z"
  }],
  "aggregate": [{
    "metricName": "com.google.calories.expended",
    "floatValue": 50.71523396112812
  }, {
    "metricName": "com.google.step_count.delta",
    "intValue": 638
  }, {
    "metricName": "com.google.distance.delta",
    "floatValue": 374.6244466607605
  }, {
    "metricName": "com.google.speed.summary",
    "floatValue": 0.4733711759850695
  }, {
    "metricName": "com.google.active_minutes",
    "intValue": 12
  }]
}